[
  {
    "title":"马云1995神预言及一张图看懂互联网产品架构",
    "brief":"最近看到马云在1995年接受浙江卫视采访时的一段旧视频，深深为马云的先见之明折服，感觉马云不会是穿越回去的吧。",
    "author":"青云",
    "createTime":"2018-12-20"
  },
  {
    "title":"程序员是青春饭吗",
    "brief":"程序员是不是青春饭，程序员三十岁后、四十岁后还能不能找到工作，能不能找个高薪工作，这几乎是程序员圈子的月经问题。",
    "author":"青云",
    "createTime":"2018-12-21"
  },
  {
    "title":"微信7.0改版及向微信学习产品设计",
    "brief":"同时微信之父张小龙更新了这样一条朋友圈，对这期微信改版发布了官方看法。 从上面两张图上可以看出，微信本期改版集中在“看”上。",
    "author":"青云",
    "createTime":"2018-12-22"
  },
  {
    "title":"圣诞快乐，你的2018年余额还剩6天",
    "brief":"圣诞来临，分享一下美轮美奂的北京APM圣诞奇境和一个有趣的故事《圣诞欢歌》。",
    "author":"青云",
    "createTime":"2018-12-25"
  },
  {
    "title":"H5、Android、JavaWeb选择哪个方向",
    "brief":"快到年末了，很多学生就要面临实习了，选择从事开发工作的计算机学生这时往往都会面临这样一个问题，选择什么职位作为自己的第一份工作呢。",
    "author":"青云",
    "createTime":"2018-12-29"
  },
  {
    "title":"泉城济南",
    "brief":"济南号称泉城，确实名副其实，全城共有七十二口名泉，到处都是清澈见底的，可直接饮用的泉水，泉水真是上天给济南人的厚爱。",
    "author":"青云",
    "createTime":"2018-12-30"
  },
  {
    "title":"病来如山倒",
    "brief":"翠山是典型的都市拼命三郎，每天忙忙碌碌，周旋与工作和生活之间。工作上是个小组长，上需要完成领导布置的项目，下需要督促组员按时完成任务。",
    "author":"青云",
    "createTime":"2019-01-11"
  },
  {
    "title":"为什么会不开心，重温马斯洛需求层次理论",
    "brief":"日常生活中，我们会时不时会遇到一些不开心的事情，时不时会与朋友或同事发生矛盾与争执。 我们为什么会不开心，又为什么会与朋友产生矛盾呢？",
    "author":"青云",
    "createTime":"2019-01-12"
  },
  {
    "title":"推荐一部电影：我妻子的一切",
    "brief":"电影刚开始，男女主角在日本偶尔相遇，然后陷入爱河。",
    "author":"青云",
    "createTime":"2019-01-13"
  },
  {
    "title":"电影--完美陌生人",
    "brief":"手机是当今每个人的黑匣子，如果把黑匣子公之于众，像玩真心话大冒险那样，大家把各自的手机放在桌子上，然后边聊天边吃喝，边等待手机消息",
    "author":"青云",
    "createTime":"2019-01-14"
  },
  {
    "title":"软件开发中的标准和规范",
    "brief":"软件开发中标准和规范特别重要。熟悉java的同学都知道，ssh前几年特别流行，ssm最近几年特别流行，而作为ssh中的spring一直从03年流...",
    "author":"青云",
    "createTime":"2019-01-16"
  },
  {
    "title":"推荐一本好书：这样写出好故事",
    "brief":"卡夫卡说：“我么应该只读那些会咬人和蜇人的书”。只有好故事才会折磨读者！",
    "author":"青云",
    "createTime":"2019-01-25"
  }
]